{ "columns":16,
 "image":"..\/..\/sprites\/proof_of_concept.png",
 "imageheight":512,
 "imagewidth":512,
 "margin":0,
 "name":"proof_of_concept",
 "spacing":0,
 "tilecount":256,
 "tiledversion":"git",
 "tileheight":32,
 "tilewidth":32,
 "type":"tileset",
 "version":"1.10",
 "wangsets":[
        {
         "colors":[
                {
                 "color":"#ff0000",
                 "name":"dirt",
                 "probability":1,
                 "tile":-1
                }, 
                {
                 "color":"#00ff00",
                 "name":"brick",
                 "probability":1,
                 "tile":-1
                }, 
                {
                 "color":"#0000ff",
                 "name":"air",
                 "probability":1,
                 "tile":-1
                }],
         "name":"poc",
         "tile":-1,
         "type":"corner",
         "wangtiles":[
                {
                 "tileid":0,
                 "wangid":[0, 3, 0, 1, 0, 3, 0, 3]
                }, 
                {
                 "tileid":1,
                 "wangid":[0, 3, 0, 1, 0, 1, 0, 3]
                }, 
                {
                 "tileid":2,
                 "wangid":[0, 3, 0, 3, 0, 1, 0, 3]
                }, 
                {
                 "tileid":3,
                 "wangid":[0, 3, 0, 2, 0, 3, 0, 3]
                }, 
                {
                 "tileid":4,
                 "wangid":[0, 3, 0, 2, 0, 2, 0, 3]
                }, 
                {
                 "tileid":5,
                 "wangid":[0, 3, 0, 3, 0, 2, 0, 3]
                }, 
                {
                 "tileid":16,
                 "wangid":[0, 1, 0, 1, 0, 3, 0, 3]
                }, 
                {
                 "tileid":17,
                 "wangid":[0, 1, 0, 1, 0, 1, 0, 1]
                }, 
                {
                 "tileid":18,
                 "wangid":[0, 3, 0, 3, 0, 1, 0, 1]
                }, 
                {
                 "tileid":19,
                 "wangid":[0, 2, 0, 2, 0, 3, 0, 3]
                }, 
                {
                 "tileid":20,
                 "wangid":[0, 2, 0, 2, 0, 2, 0, 2]
                }, 
                {
                 "tileid":21,
                 "wangid":[0, 3, 0, 3, 0, 2, 0, 2]
                }, 
                {
                 "tileid":32,
                 "wangid":[0, 1, 0, 3, 0, 3, 0, 3]
                }, 
                {
                 "tileid":33,
                 "wangid":[0, 1, 0, 3, 0, 3, 0, 1]
                }, 
                {
                 "tileid":34,
                 "wangid":[0, 3, 0, 3, 0, 3, 0, 1]
                }, 
                {
                 "tileid":35,
                 "wangid":[0, 2, 0, 3, 0, 3, 0, 3]
                }, 
                {
                 "tileid":36,
                 "wangid":[0, 2, 0, 3, 0, 3, 0, 2]
                }, 
                {
                 "tileid":37,
                 "wangid":[0, 3, 0, 3, 0, 3, 0, 2]
                }, 
                {
                 "tileid":48,
                 "wangid":[0, 3, 0, 1, 0, 1, 0, 1]
                }, 
                {
                 "tileid":49,
                 "wangid":[0, 1, 0, 1, 0, 1, 0, 3]
                }]
        }]
}